laymon/__init__.py
laymon/displays.py
laymon/exceptions.py
laymon/interfaces.py
laymon/monitor.py
laymon/monitoring.py
laymon/observers.py
laymon-1.0.1.dist-info/AUTHORS.rst
laymon-1.0.1.dist-info/LICENSE
laymon-1.0.1.dist-info/METADATA
laymon-1.0.1.dist-info/WHEEL
laymon-1.0.1.dist-info/top_level.txt
laymon-1.0.1.dist-info/RECORD
