Metadata-Version: 2.1
Name: laymon
Version: 1.0.1
Summary: A python based package used to visualize the feature maps/ layers of a neural network
Home-page: https://github.com/shubham3121/laymon
Author: Shubham Gupta
Author-email: shubhamgupta3121@gmail.com
License: MIT license
Keywords: laymon
Platform: UNKNOWN
Classifier: Intended Audience :: Developers
Classifier: License :: OSI Approved :: MIT License
Classifier: Natural Language :: English
Classifier: Topic :: Scientific/Engineering :: Visualization
Classifier: Topic :: Scientific/Engineering :: Image Recognition
Classifier: Programming Language :: Python :: 3
Classifier: Programming Language :: Python :: 3.5
Classifier: Programming Language :: Python :: 3.6
Classifier: Programming Language :: Python :: 3.7
Classifier: Programming Language :: Python :: 3.8
Requires-Python: >=3.5
Requires-Dist: pip (>=19.2.3)
Requires-Dist: wheel (>=0.33.6)
Requires-Dist: watchdog (>=0.9.0)
Requires-Dist: matplotlib (>=3.0.1)
